rho_crypto/__init__.py
rho_crypto/aes.py
rho_crypto/hashing.py
tests/fixtures/__init__.py
rho_crypto-0.5.2.dist-info/METADATA
rho_crypto-0.5.2.dist-info/WHEEL
rho_crypto-0.5.2.dist-info/top_level.txt
rho_crypto-0.5.2.dist-info/RECORD
